README.rst
setup.py
surbtc/Client.py
surbtc/Currency.py
surbtc/Market.py
surbtc/__init__.py
surbtc.egg-info/PKG-INFO
surbtc.egg-info/SOURCES.txt
surbtc.egg-info/dependency_links.txt
surbtc.egg-info/requires.txt
surbtc.egg-info/top_level.txt