Metadata-Version: 1.1
Name: surbtc
Version: 1.1.0
Summary: Cliente para servicios web de SURBTC
Home-page: https://github.com/CriptoPagos/surbtc-api-client-python
Author: Esteban De La Fuente Rubio, DeLaF
Author-email: esteban@sasco.cl
License: LGPL
Keywords: api client
Platform: UNKNOWN
Classifier: Development Status :: 5 - Production/Stable
Classifier: Intended Audience :: Developers
Classifier: Topic :: Software Development :: Build Tools
Classifier: License :: OSI Approved :: GNU Lesser General Public License v3 or later (LGPLv3+)
Classifier: Programming Language :: Python :: 2
Classifier: Programming Language :: Python :: 2.7
Classifier: Programming Language :: Python :: 3
Classifier: Programming Language :: Python :: 3.5
